pydundas/__init__.py
pydundas/dundas.py
pydundas/exceptions.py
pydundas/examples/__init__.py
pydundas/examples/constant.py
pydundas/examples/cube.py
pydundas/examples/export.py
pydundas/examples/health.py
pydundas/examples/notifications.py
pydundas/examples/project.py
pydundas/examples/session.py
pydundas/rest/__init__.py
pydundas/rest/account.py
pydundas/rest/api.py
pydundas/rest/constant.py
pydundas/rest/cube.py
pydundas/rest/dashboard.py
pydundas/rest/export.py
pydundas/rest/file.py
pydundas/rest/health.py
pydundas/rest/job.py
pydundas/rest/js.py
pydundas/rest/notification.py
pydundas/rest/project.py
pydundas/tests/__init__.py
pydundas/tests/test_pydundas.py
pydundas/tests/rest/__init__.py
pydundas/tests/rest/test_account.py
pydundas/tests/rest/test_api.py
pydundas/tests/rest/test_constant.py
pydundas/tests/rest/test_cube.py
pydundas/tests/rest/test_file.py
pydundas/tests/rest/test_health.py
pydundas/tests/rest/test_job.py
pydundas/tests/rest/test_js.py
pydundas/tests/rest/test_notification.py
pydundas/tests/rest/test_project.py
pydundas-1.6.1.dist-info/LICENSE
pydundas-1.6.1.dist-info/METADATA
pydundas-1.6.1.dist-info/WHEEL
pydundas-1.6.1.dist-info/top_level.txt
pydundas-1.6.1.dist-info/RECORD
