Metadata-Version: 2.1
Name: pydundas
Version: 1.6.1
Summary: Python interface to Dundas rest api.
Home-page: https://github.com/Web-Power/pydundas
Author: Guillaume Roger
Author-email: datatech@webpower.nl
License: MIT
Platform: UNKNOWN
Classifier: Programming Language :: Python :: 3
Classifier: License :: OSI Approved :: MIT License
Classifier: Operating System :: OS Independent
Requires-Dist: requests
Requires-Dist: pyyaml
Requires-Dist: pillow
